CryptostatsPython/Cryptostats.py
CryptostatsPython/__init__.py
Cryptostats_Python-1.0.0.dist-info/LICENSE.txt
Cryptostats_Python-1.0.0.dist-info/METADATA
Cryptostats_Python-1.0.0.dist-info/WHEEL
Cryptostats_Python-1.0.0.dist-info/top_level.txt
Cryptostats_Python-1.0.0.dist-info/RECORD
