Metadata-Version: 2.1
Name: Cryptostats-Python
Version: 1.0.0
Summary: Stream cryptocurrency data and analytics for 15,000+ instruments with a single websocket.
Home-page: https://github.com/Cryptostats/Cryptostats-Python
Author: Cryptostats
Author-email: hello@cryptostats.dev
License: UNKNOWN
Project-URL: Bug Tracker, https://github.com/Cryptostats/Cryptostats-Python/issues
Project-URL: Cryptostats, https://www.cryptostats.dev
Platform: UNKNOWN
Classifier: Programming Language :: Python :: 3
Classifier: License :: OSI Approved :: MIT License
Classifier: Operating System :: OS Independent
Requires-Python: >=3.6
Requires-Dist: ujson
Requires-Dist: websocket-client
